Metadata-Version: 1.0
Name: P8yDataFactory
Version: 0.0.1.5
Summary: a library for API test Data query
Home-page: https://git.dev.tencent.com/tywldx/P8yDataFactory.git
Author: tywldx
Author-email: tywldx@163.com
License: MIT License
Keywords: data factory
Platform: any
